.bumpversion.cfg
CONTRIBUTING.md
LICENSE
MANIFEST.in
Makefile
README.md
package-lock.json
package.json
pyproject.toml
setup.py
docs/Makefile
docs/api.md
docs/conf.py
docs/gettingstarted.md
docs/index.md
docs/make.bat
sports_box/.env
sports_box/__init__.py
sports_box/__main__.py
sports_box/_version.py
sports_box/bot.py
sports_box/fantasydata.py
sports_box/getnews.py
sports_box/getplayerstuff.py
sports_box/getteamstuff.py
sports_box/gettiktokstuff.py
sports_box/gettodayscores.py
sports_box/teamcolors.py
sports_box/userinterface.py
sports_box.egg-info/PKG-INFO
sports_box.egg-info/SOURCES.txt
sports_box.egg-info/dependency_links.txt
sports_box.egg-info/requires.txt
sports_box.egg-info/top_level.txt
sports_box/.pytest_cache/.gitignore
sports_box/.pytest_cache/CACHEDIR.TAG
sports_box/.pytest_cache/README.md
sports_box/.pytest_cache/v/cache/nodeids
sports_box/.pytest_cache/v/cache/stepwise
sports_box/dogger/dogger.png
sports_box/tests/test_all.py
sports_box/tests/.pytest_cache/.gitignore
sports_box/tests/.pytest_cache/CACHEDIR.TAG
sports_box/tests/.pytest_cache/README.md
sports_box/tests/.pytest_cache/v/cache/lastfailed
sports_box/tests/.pytest_cache/v/cache/nodeids
sports_box/tests/.pytest_cache/v/cache/stepwise