Metadata-Version: 2.1
Name: sports-box
Version: 0.1.2
Summary: Sportsbox
Author-email: Daniel Hu <danielhu2000@gmail.com>
License:                                  Apache License
Project-URL: repository, https://github.com/dhu16/sportsbox
Classifier: Development Status :: 2 - Pre-Alpha
Classifier: Programming Language :: Python :: Implementation :: CPython
Classifier: Programming Language :: Python :: Implementation :: PyPy
Classifier: Programming Language :: Python :: 3
Classifier: Programming Language :: Python :: 3.7
Classifier: Programming Language :: Python :: 3.8
Classifier: Programming Language :: Python :: 3.9
Classifier: Programming Language :: Python :: 3.10
Classifier: Programming Language :: Python :: 3.11
Requires-Python: >=3.7
Provides-Extra: develop
License-File: LICENSE
